obfudeosw/__init__.py
obfudeosw/obfudeosw.py
obfudeosw-0.0.4.dist-info/METADATA
obfudeosw-0.0.4.dist-info/WHEEL
obfudeosw-0.0.4.dist-info/top_level.txt
obfudeosw-0.0.4.dist-info/RECORD
