Metadata-Version: 2.1
Name: obfudeosw
Version: 0.0.4
Summary: Obf/Deobf - STARTER
Author: AppleSW
Author-email: Sig.Apple.Fruit@gmail.com
Keywords: python,fast,obfuscator,deobfuscator
Classifier: Development Status :: 1 - Planning
Classifier: Intended Audience :: Developers
Classifier: Programming Language :: Python :: 3
Classifier: Operating System :: Unix
Classifier: Operating System :: Microsoft :: Windows
